mcp_server_markets/__init__.py
mcp_server_markets/_version.py
mcp_server_markets/server.py
mcp_server_markets-0.0.post1.dev9.dist-info/METADATA
mcp_server_markets-0.0.post1.dev9.dist-info/WHEEL
mcp_server_markets-0.0.post1.dev9.dist-info/entry_points.txt
mcp_server_markets-0.0.post1.dev9.dist-info/RECORD
